scope/README.md
scope/__init__.py
scope/callgraph/__init__.py
scope/callgraph/builder.py
scope/callgraph/constants.py
scope/callgraph/logging.py
scope/callgraph/treesitter.py
scope/callgraph/utils.py
scope/callgraph/api/CallGraph.py
scope/callgraph/api/FileGraph.py
scope/callgraph/api/__init__.py
scope/callgraph/dtos/Alias.py
scope/callgraph/dtos/CallStack.py
scope/callgraph/dtos/CallTree.py
scope/callgraph/dtos/Definition.py
scope/callgraph/dtos/Range.py
scope/callgraph/dtos/Reference.py
scope/callgraph/dtos/Symbol.py
scope/callgraph/dtos/__init__.py
scope/callgraph/dtos/config/CallGraphBuilderConfig.py
scope/callgraph/dtos/config/__init__.py
scope/callgraph/enums/AllowedLanguages.py
scope/callgraph/enums/AllowedSymbols.py
scope/callgraph/enums/CallTreeType.py
scope/callgraph/enums/LSPSymbolType.py
scope/callgraph/enums/ReferenceType.py
scope/callgraph/enums/TreeSitterNodeVariant.py
scope/callgraph/enums/__init__.py
scope/callgraph/resources/__init__.py
scope/callgraph/resources/languages.py
scope/callgraph/resources/tree_sitter.py
codescope-1.0.1.dist-info/METADATA
codescope-1.0.1.dist-info/WHEEL
codescope-1.0.1.dist-info/licenses/LICENSE
codescope-1.0.1.dist-info/RECORD
