Metadata-Version: 2.4
Name: codescope
Version: 1.0.1
Summary: A call graph generator designed for codebase RAG
Project-URL: homepage, https://useadrenaline.com
Project-URL: repository, https://github.com/adrenaline-ai/scope
Author-email: Michael Usachenko <michael@useadrenaline.com>
Maintainer-email: Michael Usachenko <michael@useadrenaline.com>, Jonathan Shobrook <jonathan@useadrenaline.com>
License:                                  Apache License
License-File: LICENSE
Classifier: Development Status :: 4 - Beta
Classifier: Programming Language :: Python
Requires-Python: <3.13,>=3.10
Requires-Dist: httpx[http2]>=0.28.1
Requires-Dist: igraph>=0.11.8
Requires-Dist: leidenalg>=0.10.2
Requires-Dist: loguru>=0.7.3
Requires-Dist: multilspy>=0.0.15
Requires-Dist: orjson>=3.10
Requires-Dist: rich>=13.9.4
Requires-Dist: rustworkx>=0.16.0
Requires-Dist: tqdm>=4.67.1
Requires-Dist: tree-sitter-languages>=1.10.2
Requires-Dist: tree-sitter==0.21.3
Requires-Dist: withrepo==0.2.4
